prescience/__init__.py
prescience/agents.py
prescience/atari_wrappers.py
prescience/model_check_noop.py
prescience/labelling/Assault.py
prescience/labelling/Below_Reward.py
prescience/labelling/Bowling.py
prescience/labelling/Death.py
prescience/labelling/DoubleDunk.py
prescience/labelling/Freeway.py
prescience/labelling/Frostbite.py
prescience/labelling/Gravitar.py
prescience/labelling/Hero.py
prescience/labelling/InstantNegativeReward.py
prescience/labelling/KungFuMaster.py
prescience/labelling/Labeller.py
prescience/labelling/Seaquest.py
prescience/labelling/__init__.py
prescience/labelling/properties.py
bounded_prescience-0.0.3.dist-info/LICENSE
bounded_prescience-0.0.3.dist-info/METADATA
bounded_prescience-0.0.3.dist-info/WHEEL
bounded_prescience-0.0.3.dist-info/top_level.txt
bounded_prescience-0.0.3.dist-info/RECORD
