Metadata-Version: 2.1
Name: bounded-prescience
Version: 0.0.3
Summary: Shielding Atari Games with Bounded Prescience
Home-page: https://github.com/HjalmarWijk/bounded-prescience
Author: Hjalmar Wijk, Hosein Hasanbeig, Mirco Giacobbe, Daniel Kroening
Author-email: hjalmar.wijk@gmail.com, hosein.hasanbeig@icloud.com
License: UNKNOWN
Keywords: rl,safety,atari,agent
Platform: UNKNOWN
Classifier: Programming Language :: Python :: 3
Classifier: License :: OSI Approved :: BSD License
Classifier: Operating System :: OS Independent
Requires-Python: >=3.5
Requires-Dist: chainer
Requires-Dist: chainerrl
Requires-Dist: numpy
Requires-Dist: Pillow
Requires-Dist: gym
Requires-Dist: gym[atari]
Requires-Dist: cmake
Requires-Dist: opencv-python
Requires-Dist: tensorflow
